CyrilAlpha/__init__.py
CyrilAlpha/Module/Cyril_analyse.cp38-win_amd64.pyd
CyrilAlpha/Module/Cyril_context.cp38-win_amd64.pyd
CyrilAlpha/Module/Cyril_module.cp38-win_amd64.pyd
CyrilAlpha/Module/Cyril_operators.cp38-win_amd64.pyd
CyrilAlpha/Module/Cyril_tradingday.cp38-win_amd64.pyd
CyrilAlpha/Module/__init__.py
CyrilAlpha/Module/futures_attributes.csv
CyrilAlpha/Module/holidays.csv
CyrilAlpha/Module/universes.txt
CyrilAlpha-1.1.dist-info/METADATA
CyrilAlpha-1.1.dist-info/WHEEL
CyrilAlpha-1.1.dist-info/top_level.txt
CyrilAlpha-1.1.dist-info/RECORD
